<?xml version="1.0" encoding="UTF-8"?>
<extend_features>
	<app_feature name="com.android.phone.replace_network_title_dynamic" args="StringList:array">
		<StringList name="array" args="4G;LTE"/>
	</app_feature>
	<app_feature name="com.android.phone.network_list_visible_dynamic" args="String:show"/>
	<app_feature name="com.android.phone.network_list_visible_5G_dynamic" args="String:show"/>
	<app_feature name="com.android.phone.customize_network_value_list_5g_dynamic" args="StringList:type">
		<StringList name="type" args="33;9"/>
	</app_feature>
	<app_feature name="com.android.phone.customize_network_name_list_5g_dynamic" args="StringList:type">
		<StringList name="type" args="oplus_5g_lte_3g_2g_auto;oplus_lte_3g_2g_auto"/>
	</app_feature>
	<app_feature name="com.android.phone.customize_network_value_list_dynamic" args="StringList:type">
		<StringList name="type" args="9"/>
	</app_feature>
	<app_feature name="com.android.phone.customize_network_name_list_dynamic" args="StringList:type">
		<StringList name="type" args="oplus_lte_3g_2g_auto"/>
	</app_feature>
	<app_feature name="com.android.phone.simsettings.customize_vowifi_title_dynamic" args="StringList:value">
		<StringList name="value" args="key_vowifi_language;pl;key_vowifi_title;wifi_call_title_for_pl_tmobile"/>
	</app_feature>
	<app_feature name="com.android.systemui.show_2g_for_e"/>
	<app_feature name="com.android.systemui.show_3g_for_h"/>
	<app_feature name="com.android.systemui.show_lteplus_for_4gplus"/>
	<app_feature name="com.android.settings.need_show_2g3g"/>
	<app_feature name="com.android.systemui.show_lte_for_4g"/>
</extend_features>
<!-- Timestamp 2023-09-19T11:04:16 #47302 -->
